conda_pkm_repo/pkm_extension.py
conda_pkm_repo/conda_repo.py
conda_pkm_repo/conda_distribution.py
conda_pkm_repo/__init__.py
conda_pkm_repo/conda_channel_subdir.py
conda_pkm_repo-0.1.0.dist-info/LICENSE
conda_pkm_repo-0.1.0.dist-info/WHEEL
conda_pkm_repo-0.1.0.dist-info/METADATA
conda_pkm_repo-0.1.0.dist-info/entry_points.txt
